convertor/__init__.py
convertor/convertor.py
compose_to_manifest-0.0.8.dist-info/LICENSE
compose_to_manifest-0.0.8.dist-info/METADATA
compose_to_manifest-0.0.8.dist-info/WHEEL
compose_to_manifest-0.0.8.dist-info/entry_points.txt
compose_to_manifest-0.0.8.dist-info/top_level.txt
compose_to_manifest-0.0.8.dist-info/RECORD
