Metadata-Version: 2.1
Name: compose-to-manifest
Version: 0.0.8
Summary: Convert Docker Compose project to Azure IoT Edge deployment manifest
Home-page: https://github.com/VSChina/compose-to-manifest
Author: typeli
Author-email: juncli@outlook.com
License: UNKNOWN
Platform: UNKNOWN
Classifier: Programming Language :: Python :: 3
Requires-Python: >=3.6.0
Requires-Dist: docker-compose
